include/GLFW/glfw3.h
include/GLFW/glfw3native.h
include/gmock/gmock-actions.h
include/gmock/gmock-cardinalities.h
include/gmock/gmock-function-mocker.h
include/gmock/gmock-matchers.h
include/gmock/gmock-more-actions.h
include/gmock/gmock-more-matchers.h
include/gmock/gmock-nice-strict.h
include/gmock/gmock-spec-builders.h
include/gmock/gmock.h
include/gmock/internal/custom/gmock-generated-actions.h
include/gmock/internal/custom/gmock-matchers.h
include/gmock/internal/custom/gmock-port.h
include/gmock/internal/custom/README.md
include/gmock/internal/gmock-internal-utils.h
include/gmock/internal/gmock-port.h
include/gmock/internal/gmock-pp.h
include/gtest/gtest-assertion-result.h
include/gtest/gtest-death-test.h
include/gtest/gtest-matchers.h
include/gtest/gtest-message.h
include/gtest/gtest-param-test.h
include/gtest/gtest-printers.h
include/gtest/gtest-spi.h
include/gtest/gtest-test-part.h
include/gtest/gtest-typed-test.h
include/gtest/gtest.h
include/gtest/gtest_pred_impl.h
include/gtest/gtest_prod.h
include/gtest/internal/custom/gtest-port.h
include/gtest/internal/custom/gtest-printers.h
include/gtest/internal/custom/gtest.h
include/gtest/internal/custom/README.md
include/gtest/internal/gtest-death-test-internal.h
include/gtest/internal/gtest-filepath.h
include/gtest/internal/gtest-internal.h
include/gtest/internal/gtest-param-util.h
include/gtest/internal/gtest-port-arch.h
include/gtest/internal/gtest-port.h
include/gtest/internal/gtest-string.h
include/gtest/internal/gtest-type-util.h
lib/cmake/glfw3/glfw3Config.cmake
lib/cmake/glfw3/glfw3ConfigVersion.cmake
lib/cmake/glfw3/glfw3Targets-release.cmake
lib/cmake/glfw3/glfw3Targets.cmake
lib/cmake/GTest/GTestConfig.cmake
lib/cmake/GTest/GTestConfigVersion.cmake
lib/cmake/GTest/GTestTargets-release.cmake
lib/cmake/GTest/GTestTargets.cmake
lib/glfw3.lib
lib/gmock.lib
lib/gmock_main.lib
lib/gtest.lib
lib/gtest_main.lib
lib/pkgconfig/glfw3.pc
lib/pkgconfig/gmock.pc
lib/pkgconfig/gmock_main.pc
lib/pkgconfig/gtest.pc
pyaccell-1.0.0.dist-info/METADATA
pyaccell-1.0.0.dist-info/WHEEL
pyaccell-1.0.0.dist-info/licenses/LICENSE
pyaccell-1.0.0.dist-info/RECORD
