Metadata-Version: 2.1
Name: pyaccell
Version: 1.0.0
Summary: A GPU Accelerated Cellular Automata Library
Author-Email: Syed Ahmed Hussain <ahmedhus22@gmail.com>
Classifier: License :: OSI Approved :: MIT License
Project-URL: Homepage, https://github.com/ahmedhus22/pyaccell
Requires-Python: >=3.8
